setup.py
PingdomBackup.egg-info/PKG-INFO
PingdomBackup.egg-info/SOURCES.txt
PingdomBackup.egg-info/dependency_links.txt
PingdomBackup.egg-info/entry_points.txt
PingdomBackup.egg-info/requires.txt
PingdomBackup.egg-info/top_level.txt
pingdombackup/Database.py
pingdombackup/Pingdom.py
pingdombackup/PingdomBackup.py
pingdombackup/__init__.py
pingdombackup/log.py
pingdombackup/tool.py