Metadata-Version: 1.1
Name: PingdomBackup
Version: 0.2.2
Summary: Backup Pingdom logs
Home-page: https://github.com/joelverhagen/PingdomBackup
Author: Joel Verhagen
Author-email: joel.verhagen@gmail.com
License: MIT
Platform: UNKNOWN
Classifier: Development Status :: 3 - Alpha
Classifier: Intended Audience :: Developers
Classifier: Intended Audience :: System Administrators
Classifier: License :: OSI Approved :: MIT License
Classifier: Operating System :: OS Independent
Classifier: Topic :: System :: Monitoring
Classifier: Programming Language :: Python :: 3
